app.py
run.py
data_science_visualization_assistant-0.3.0.dist-info/licenses/LICENSE
src/__init__.py
src/ds_assistant/__init__.py
src/ds_assistant/chat_completions/__init__.py
src/ds_assistant/chat_completions/llm_chat_completions.py
src/ds_assistant/sandbox/__init__.py
src/ds_assistant/sandbox/e2b_code_interpreter.py
src/ds_assistant/utils/__init__.py
src/ds_assistant/utils/some_utils.py
data_science_visualization_assistant-0.3.0.dist-info/METADATA
data_science_visualization_assistant-0.3.0.dist-info/WHEEL
data_science_visualization_assistant-0.3.0.dist-info/entry_points.txt
data_science_visualization_assistant-0.3.0.dist-info/top_level.txt
data_science_visualization_assistant-0.3.0.dist-info/RECORD
