Metadata-Version: 2.4
Name: data-science-visualization-assistant
Version: 0.3.0
Summary: LLM-powered Data Science & Visualization Assistant with Streamlit
Home-page: https://github.com/Vishnuu011/data-science-visualization-assistant
Author: Vishnu
Author-email: Vishnu <vishnurrajeev@gmail.com>
License: MIT
Project-URL: Homepage, https://github.com/Vishnuu011/data-science-visualization-assistant
Project-URL: Repository, https://github.com/Vishnuu011/data-science-visualization-assistant
Project-URL: Issues, https://github.com/Vishnuu011/data-science-visualization-assistant/issues
Requires-Python: >=3.8
License-File: LICENSE
Requires-Dist: e2b-code-interpreter==1.0.3
Requires-Dist: pandas
Requires-Dist: numpy
Requires-Dist: matplotlib
Requires-Dist: streamlit
Requires-Dist: e2b
Requires-Dist: Pillow
Requires-Dist: python-dotenv
Requires-Dist: groq
Dynamic: author
Dynamic: home-page
Dynamic: license-file
Dynamic: requires-python
